python_pushover_open_client/__init__.py
python_pushover_open_client/__main__.py
python_pushover_open_client-0.0.15.dist-info/LICENSE.txt
python_pushover_open_client-0.0.15.dist-info/METADATA
python_pushover_open_client-0.0.15.dist-info/WHEEL
python_pushover_open_client-0.0.15.dist-info/entry_points.txt
python_pushover_open_client-0.0.15.dist-info/top_level.txt
python_pushover_open_client-0.0.15.dist-info/RECORD
